astrovascpy/PetscBinaryIO.py
astrovascpy/__init__.py
astrovascpy/bloodflow.py
astrovascpy/exceptions.py
astrovascpy/io.py
astrovascpy/ou.py
astrovascpy/plotting.py
astrovascpy/report_reader.py
astrovascpy/report_writer.py
astrovascpy/scipy_petsc_conversions.py
astrovascpy/typing.py
astrovascpy/utils.py
astrovascpy/version.py
astrovascpy/vtk_io.py
AstroVascPy-0.1.4.dist-info/AUTHORS.txt
AstroVascPy-0.1.4.dist-info/LICENSE.txt
AstroVascPy-0.1.4.dist-info/METADATA
AstroVascPy-0.1.4.dist-info/WHEEL
AstroVascPy-0.1.4.dist-info/entry_points.txt
AstroVascPy-0.1.4.dist-info/top_level.txt
AstroVascPy-0.1.4.dist-info/RECORD
