Metadata-Version: 2.1
Name: AstroVascPy
Version: 0.1.4
Summary: Simulating blood flow in vasculature
Home-page: https://github.com/BlueBrain/AstroVascPy
Author: Blue Brain Project, EPFL
License: Apache-2
Project-URL: Tracker, https://github.com/BlueBrain/AstroVascpy/issues
Project-URL: Source, https://github.com/BlueBrain/AstroVascPy
Classifier: Development Status :: 5 - Production/Stable
Classifier: Intended Audience :: Education
Classifier: Intended Audience :: Science/Research
Classifier: Programming Language :: Python :: 3
Classifier: Topic :: Scientific/Engineering :: Bio-Informatics
Requires-Python: >=3.10
License-File: LICENSE.txt
License-File: AUTHORS.txt
Requires-Dist: click
Requires-Dist: cached-property
Requires-Dist: scipy
Requires-Dist: numpy
Requires-Dist: h5py
Requires-Dist: networkx
Requires-Dist: morphio
Requires-Dist: vascpy
Requires-Dist: matplotlib
Requires-Dist: seaborn
Requires-Dist: tqdm
Requires-Dist: pyyaml
Requires-Dist: pandas <2.0.0
Requires-Dist: tables
Requires-Dist: coverage
Requires-Dist: libsonata
Requires-Dist: trimesh
Requires-Dist: cython
Requires-Dist: psutil
Provides-Extra: docs
Requires-Dist: m2r2 ; extra == 'docs'
Requires-Dist: sphinx ; extra == 'docs'
Requires-Dist: sphinx-bluebrain-theme ; extra == 'docs'
Requires-Dist: sphinx-click ; extra == 'docs'
Provides-Extra: test
Requires-Dist: pytest ; extra == 'test'
Requires-Dist: pytest-mpi ; extra == 'test'
Provides-Extra: viz
Requires-Dist: vtk ; extra == 'viz'
